casimats_inspect/__init__.py
casimats_inspect/provider.py
casimats_inspect-0.1.0.dist-info/METADATA
casimats_inspect-0.1.0.dist-info/WHEEL
casimats_inspect-0.1.0.dist-info/entry_points.txt
casimats_inspect-0.1.0.dist-info/top_level.txt
casimats_inspect-0.1.0.dist-info/RECORD
