Metadata-Version: 2.4
Name: casimats-inspect
Version: 0.1.0
Requires-Dist: inspect-ai
